mongolog/__init__.py
mongolog/handlers.py
mongolog/logger.py
mongolog/tests.py
mongo_py_logger-1.8.2.dist-info/LICENSE
mongo_py_logger-1.8.2.dist-info/METADATA
mongo_py_logger-1.8.2.dist-info/WHEEL
mongo_py_logger-1.8.2.dist-info/top_level.txt
mongo_py_logger-1.8.2.dist-info/RECORD
