Metadata-Version: 2.1
Name: mongo-py-logger
Version: 1.8.2
Summary: Logger for python, with MongoHandler.
Home-page: https://github.com/razens/mongo-py-logger
Author: Andrey Arambitsky
Author-email: razens@gmail.com
License: MIT
Keywords: Logger Logging Log
Platform: UNKNOWN
Classifier: Development Status :: 4 - Beta
Classifier: Intended Audience :: Developers
Classifier: Topic :: Software Development :: Build Tools
Classifier: License :: OSI Approved :: MIT License
Classifier: Programming Language :: Python :: 2.7
Requires-Dist: pymongo
Requires-Dist: packaging (==16.8)
Provides-Extra: dev
Requires-Dist: check-manifest ; extra == 'dev'
Provides-Extra: test
Requires-Dist: coverage ; extra == 'test'
